pyproject_appimage/__init__.py
pyproject_appimage/__main__.py
pyproject_appimage/default.png
pyproject_appimage/version.txt
pyproject_appimage-4.2.dist-info/licenses/LICENSE
pyproject_appimage-4.2.dist-info/METADATA
pyproject_appimage-4.2.dist-info/WHEEL
pyproject_appimage-4.2.dist-info/entry_points.txt
pyproject_appimage-4.2.dist-info/top_level.txt
pyproject_appimage-4.2.dist-info/RECORD
