Metadata-Version: 2.4
Name: pyproject-appimage
Version: 4.2
Summary: Generate AppImages from your Python projects
Author-email: JakobDev <jakobdev@gmx.de>
License-Expression: BSD-2-Clause
Project-URL: Downloads, https://codeberg.org/JakobDev/pyproject-appimage/releases
Project-URL: Issues, https://codeberg.org/JakobDev/pyproject-appimage/issues
Project-URL: Source, https://codeberg.org/JakobDev/pyproject-appimage
Project-URL: Donation, https://ko-fi.com/jakobdev
Keywords: JakobDev,AppImage
Classifier: Development Status :: 5 - Production/Stable
Classifier: Intended Audience :: Developers
Classifier: Environment :: Other Environment
Classifier: Topic :: Games/Entertainment
Classifier: Operating System :: POSIX :: Linux
Classifier: Programming Language :: Python :: 3
Classifier: Programming Language :: Python :: 3.9
Classifier: Programming Language :: Python :: 3.10
Classifier: Programming Language :: Python :: 3.11
Classifier: Programming Language :: Python :: 3.12
Classifier: Programming Language :: Python :: 3.13
Classifier: Programming Language :: Python :: 3 :: Only
Classifier: Programming Language :: Python :: Implementation :: CPython
Requires-Python: >=3.9
License-File: LICENSE
Requires-Dist: requests
Requires-Dist: desktop-entry-lib
Requires-Dist: tomli; python_version < "3.11"
Dynamic: license-file
